{"name":"books","bookList":[{"date":"2013-06-08","title":"\u4eac\u90fd\u81ea\u52a9\u8d85\u7c21\u55ae","price":"211","imageUrl":"http:\/\/addons.books.com.tw\/G\/001\/2\/0010537122.jpg","link":"http:\/\/www.books.com.tw\/exep\/prod\/booksfile.php?item=0010537122"},{"date":"2013-06-09","title":"\u6cd5\u91ab\uff0e\u5c4d\u9ad4\uff0e\u89e3\u5256\u5ba4\uff1a\u72af\u7f6a\u641c\u67e5216\u554f-\u5c08...","price":"251","imageUrl":"http:\/\/addons.books.com.tw\/G\/001\/7\/0010574237.jpg","link":"http:\/\/www.books.com.tw\/exep\/prod\/booksfile.php?item=0010574237"}]}