{"name":"books","bookList":[{"date":"2014-08-09","title":"\u925b\u7b46\u756b\u65b0\u624b\u7684\u7b2c\u4e00\u672c\u66f8\uff1a3\u500b\u6b65\u9a5f\u300181\u500b\u7bc4...","price":"172","imageUrl":"http:\/\/www.books.com.tw\/img\/001\/062\/68\/0010626804.jpg","link":"http:\/\/www.books.com.tw\/products\/0010626804"},{"date":"2014-08-04","title":"\u611b\u5fb7\u83ef\u7684\u795e\u5947\u65c5\u884c","price":"185","imageUrl":"http:\/\/www.books.com.tw\/img\/001\/034\/92\/0010349202.jpg","link":"http:\/\/www.books.com.tw\/products\/0010349202"},{"date":"2014-08-05","title":"\u597d\u554f\u984c\uff0c\u5efa\u7acb\u597d\u95dc\u4fc2\uff1a\u8f49\u8b8a\u5de5\u4f5c\u3001\u4eba\u969b\u548c\u5bb6\u5ead...","price":"198","imageUrl":"http:\/\/www.books.com.tw\/img\/001\/063\/15\/0010631562.jpg","link":"http:\/\/www.books.com.tw\/products\/0010631562"},{"date":"2014-08-06","title":"\u5091\u7c73\uff0e\u5967\u5229\u4f5b\u7701\u9322\u4e0a\u83dc","price":"343","imageUrl":"http:\/\/www.books.com.tw\/img\/001\/063\/34\/0010633486.jpg","link":"http:\/\/www.books.com.tw\/products\/0010633486"},{"date":"2014-08-07","title":"\u5c08\u6ce8\u7684\u529b\u91cf\uff1a\u4e0d\u518d\u5206\u5fc3\u7684\u81ea\u6211\u935b\u934a\uff0c\u8b93\u4f60\u638c\u63e1...","price":"251","imageUrl":"http:\/\/www.books.com.tw\/img\/001\/063\/12\/0010631218.jpg","link":"http:\/\/www.books.com.tw\/products\/0010631218"},{"date":"2014-08-08","title":"\u925b\u7b46\u756b\u65b0\u624b\u7684\u7b2c\u4e00\u672c\u66f8\uff1a3\u500b\u6b65\u9a5f\u300181\u500b\u7bc4...","price":"172","imageUrl":"http:\/\/www.books.com.tw\/img\/001\/062\/68\/0010626804.jpg","link":"http:\/\/www.books.com.tw\/products\/0010626804"},{"date":"2014-08-09","title":"\u65b0\u7248  \u5496\u5561\u5b78 COFFEEOLOGY ...","price":"343","imageUrl":"http:\/\/www.books.com.tw\/img\/001\/062\/64\/0010626423.jpg","link":"http:\/\/www.books.com.tw\/products\/0010626423"},{"date":"2014-08-10","title":"\u5168\u65b0\uff01NEW TOEIC\u65b0\u591a\u76ca\u95b1\u8b80\u984c\u5eab\u89e3...","price":"581","imageUrl":"http:\/\/www.books.com.tw\/img\/001\/063\/30\/0010633060.jpg","link":"http:\/\/www.books.com.tw\/products\/0010633060"}]}