{"name":"books","bookList":[{"date":"2014-04-11","title":"\u91ce\u7378\u82b1\u5712\uff1a1933\uff0c\u7d0d\u7cb9\u5e1d\u570b\u5143\u5e74\uff0c\u4e00\u500b\u7f8e...","price":"251","imageUrl":"http:\/\/www.books.com.tw\/img\/001\/062\/13\/0010621325.jpg","link":"http:\/\/www.books.com.tw\/products\/0010621325"},{"date":"2014-04-12","title":"\u706b\u8eca\u6162\u8dd1\uff0119\u7a2e\u4f60\u6c92\u770b\u904e\u7684\u5317\u6d77\u9053","price":"224","imageUrl":"http:\/\/www.books.com.tw\/img\/001\/061\/92\/0010619256.jpg","link":"http:\/\/www.books.com.tw\/products\/0010619256"},{"date":"2014-04-13","title":"\u6212\u6389\u721b\u82f1\u65872\uff1a\u8077\u5834\u82f1\u6587\u7684\u660e\u898f\u5247\u8207\u6f5b\u898f\u5247","price":"198","imageUrl":"http:\/\/www.books.com.tw\/img\/001\/062\/16\/0010621693.jpg","link":"http:\/\/www.books.com.tw\/products\/0010621693"}]}