{"name":"cite","bookList":[{"date":"2016-11-17","title":"Fortnum &amp; Mason\u82f1\u5f0f\u767e\u5e74\u7d93...","price":"251","imageUrl":"http:\/\/cdn.cite.com.tw\/thumbs\/MG0012.jpg","link":"http:\/\/www.cite.com.tw\/product_info.php?products_id=67663"},{"date":"2016-11-18","title":"\u7528\u5fc3\u667a\u5716\u6cd5\u958b\u767c\u5b69\u5b50\u7684\u5de6\u53f3\u8166\uff1a\u6559\u51fa\u5bcc\u6709\u5275\u610f...","price":"231","imageUrl":"http:\/\/cdn.cite.com.tw\/thumbs\/BU1026.jpg","link":"http:\/\/www.cite.com.tw\/product_info.php?products_id=68532"},{"date":"2016-11-19","title":"\u767e\u5408\u5fc3","price":"185","imageUrl":"http:\/\/cdn.cite.com.tw\/thumbs\/1UR001.jpg","link":"http:\/\/www.cite.com.tw\/product_info.php?products_id=31100"},{"date":"2016-11-20","title":"\u65e5\u672c\u6599\u7406\uff0c\u539f\u4f86\u5982\u6b64\uff1a\u7f8e\u5473\u53c8\u4e0d\u5931\u79ae\u7684\u65e5\u672c\u6599...","price":"238","imageUrl":"http:\/\/cdn.cite.com.tw\/thumbs\/1GX808.jpg","link":"http:\/\/www.cite.com.tw\/product_info.php?products_id=68514"},{"date":"2016-11-21","title":"\u804a\u5f97\u6709\u54c1\u5473\uff1a\u638c\u63e1\u8a71\u984c\uff0c\u7576\u500b\u6709\u683c\u8abf\u53c8\u9b45\u529b\u56db...","price":"231","imageUrl":"http:\/\/cdn.cite.com.tw\/thumbs\/BU3086.jpg","link":"http:\/\/www.cite.com.tw\/product_info.php?products_id=68513"},{"date":"2016-11-22","title":"Dr.\u5c0f\u5fd7\u5fd7\u5716\u89e3\u5065\u5eb7\u91ab\u5b78","price":"264","imageUrl":"http:\/\/cdn.cite.com.tw\/thumbs\/BH2015.jpg","link":"http:\/\/www.cite.com.tw\/product_info.php?products_id=68871"},{"date":"2016-11-23","title":"\u68c9\u82b1\u7cd6\u7684\u8a98\u60d1\uff1a\u5f9e\u8166\u795e\u7d93\u79d1\u5b78\u770b\u81ea\u5236\u529b","price":"224","imageUrl":"http:\/\/cdn.cite.com.tw\/thumbs\/BU0126.jpg","link":"http:\/\/www.cite.com.tw\/product_info.php?products_id=68519"}]}