{"name":"iread","bookList":[{"date":"2014-09-19","title":"\u6734\u69ff\u60e0\u50b3\uff1a\u53ea\u8981\u4e0d\u7d55\u671b\uff0c\u5c31\u6703\u6709\u5e0c\u671b","price":"231","imageUrl":"http:\/\/www.iread.com.tw\/ProductFile\/B000284488-S.jpg","link":"http:\/\/www.iread.com.tw\/ProdDetails.aspx?prodid=B000284488"},{"date":"2014-09-20","title":"\u544a\u5225\u5931\u7720\uff0c\u6578\u7f8a\u7684\u65e5\u5b50bye-bye\uff01","price":"185","imageUrl":"http:\/\/www.iread.com.tw\/ProductFile\/B000200290-S.jpg","link":"http:\/\/www.iread.com.tw\/ProdDetails.aspx?prodid=B000200290"},{"date":"2014-09-21","title":"\u624b\u4f5c\u4eba\u7684\u79c1\u85cf\uff01\u9752\u6728\u548c\u5b50\u7684\u5ead\u5712\u82b1\u8349\u523a...","price":"231","imageUrl":"http:\/\/www.iread.com.tw\/ProductFile\/B000285294-S.jpg","link":"http:\/\/www.iread.com.tw\/ProdDetails.aspx?prodid=B000285294"},{"date":"2014-09-22","title":"\u53f2\u4e0a\u6700\u5f37\uff01\u75bc\u75db\u6d88\u9664\u8056\u7d93\uff1a\u6bcf\u59295\u5206\u9418\uff0c...","price":"251","imageUrl":"http:\/\/www.iread.com.tw\/ProductFile\/B000284954-S.jpg","link":"http:\/\/www.iread.com.tw\/ProdDetails.aspx?prodid=B000284954"},{"date":"2014-09-23","title":"\u8b0e\u6a23\u7684\u6e05\u660e\u4e0a\u6cb3\u5716","price":"238","imageUrl":"http:\/\/www.iread.com.tw\/ProductFile\/B000246962-S.jpg","link":"http:\/\/www.iread.com.tw\/ProdDetails.aspx?prodid=B000246962"},{"date":"2014-09-24","title":"\u6771\u4eac\u5c0f\u5c4b\u7684\u56de\u61b6","price":"185","imageUrl":"http:\/\/www.iread.com.tw\/ProductFile\/B000284915-S.jpg","link":"http:\/\/www.iread.com.tw\/ProdDetails.aspx?prodid=B000284915"},{"date":"2014-09-25","title":"\u5716\u89e3\u8056\u7d93\uff08\u65b0\u7248\uff09","price":"251","imageUrl":"http:\/\/www.iread.com.tw\/ProductFile\/B000285166-S.jpg","link":"http:\/\/www.iread.com.tw\/ProdDetails.aspx?prodid=B000285166"}]}