{"name":"iread","bookList":[{"date":"2016-09-30","title":"\u7576\u6211\u8001\u53bb\uff1a\u8fce\u63a5\u5e73\u975c\u89ba\u9192\u7684\u665a\u5e74","price":"304","imageUrl":"http:\/\/www.iread.com.tw\/ProductFile\/B000349766-S.jpg","link":"http:\/\/www.iread.com.tw\/ProdDetails.aspx?prodid=B000349766"},{"date":"2016-10-01","title":"\u6211\u75287,000\u55ae\u5b57\u5b78\u597d\u82f1\u6587\uff081MP3\uff09","price":"263","imageUrl":"http:\/\/www.iread.com.tw\/ProductFile\/B000256570-S.jpg","link":"http:\/\/www.iread.com.tw\/ProdDetails.aspx?prodid=B000256570"},{"date":"2016-10-02","title":"\u597d\u7b11\u83ef\u5a1f\u649e\u898b\u7dad\u4e5f\u7d0d\u5496\u5561","price":"191","imageUrl":"http:\/\/www.iread.com.tw\/ProductFile\/B000234338-S.jpg","link":"http:\/\/www.iread.com.tw\/ProdDetails.aspx?prodid=B000234338"},{"date":"2016-10-03","title":"\u7576\u6536\u5165\u53ea\u5920\u586b\u98fd\u809a\u5b50\uff1a\u8d70\u5411\u8ca7\u7aae\u5316\u7684\u5e74...","price":"211","imageUrl":"http:\/\/www.iread.com.tw\/ProductFile\/B000351914-S.jpg","link":"http:\/\/www.iread.com.tw\/ProdDetails.aspx?prodid=B000351914"},{"date":"2016-10-04","title":"\u8eab\u9ad4\u524d\u5f4e\u53ca\u9ad6\u95dc\u7bc0\u4f38\u5c55\u745c\u4f3d\uff1a\u77ef\u6b63\u9aa8\u76c6...","price":"363","imageUrl":"http:\/\/www.iread.com.tw\/ProductFile\/B000275637-S.jpg","link":"http:\/\/www.iread.com.tw\/ProdDetails.aspx?prodid=B000275637"},{"date":"2016-10-05","title":"\u53cd\u6d3e\u7684\u529b\u91cf\uff1a\u5f71\u53f2\u7d93\u5178\u53cd\u6d3e\u4eba\u7269\uff0c\u6709\u4f60...","price":"205","imageUrl":"http:\/\/www.iread.com.tw\/ProductFile\/B000320258-S.jpg","link":"http:\/\/www.iread.com.tw\/ProdDetails.aspx?prodid=B000320258"}]}