{"name":"kadokawa","bookList":[{"date":"2013-04-21","title":"\u4e16\u754c\u4e00\u521d\u6200 \uff5e\u5c0f\u91ce\u5bfa\u5f8b\u7684\u60c5\u6cc1\uff5e","price":"79","imageUrl":"http:\/\/www.kadokawa.com.tw\/Upload\/711818996754257.jpg","link":"http:\/\/www.kadokawa.com.tw\/p1-products_detail.php?id=a369ugbxz2AQKb1BE8LCq5fvW_YDLTOTxVs_-Ty2dCJk"},{"date":"2013-04-22","title":"\u9b54\u528d\u59ec\uff01 (1)","price":"73","imageUrl":"http:\/\/www.kadokawa.com.tw\/Upload\/516535982881403.jpg","link":"http:\/\/www.kadokawa.com.tw\/p1-products_detail.php?id=8887JLjoYEaIg9dCi1bcJqDo8akyjvAIgb2W8w0rWPQ"},{"date":"2013-04-23","title":"\u6d41\u6dda\u7684\u7d42\u7a76\u662f\u59b3","price":"158","imageUrl":"http:\/\/www.kadokawa.com.tw\/Upload\/product_201205231532411.jpg","link":"http:\/\/www.kadokawa.com.tw\/p1-products_detail.php?id=82f65OUXug_bYgTvhIJwb4i_RQoNTwk_plQ71u8Agy4i"},{"date":"2013-04-24","title":"CODE GEASS \u5a1c\u5a1c\u8389\u7684\u5922\u9b58 (1...","price":"363","imageUrl":"http:\/\/www.kadokawa.com.tw\/Upload\/product_201303181802391.jpg","link":"http:\/\/www.kadokawa.com.tw\/p1-products_detail.php?id=1a16_9UJWn-AUSMltuZ0d-icYO3bFeJkrFAe41xh9vZd"},{"date":"2013-04-25","title":"\u6a5f\u52d5\u6230\u58eb\u6d77\u76dc\u92fc\u5f48 (1)\u3001(2)","price":"158","imageUrl":"http:\/\/www.kadokawa.com.tw\/Upload\/product_201303181810341.jpg","link":"http:\/\/www.kadokawa.com.tw\/p1-products_detail.php?id=53b9TMxU10LM2sMOWpyU6Br-5zN_Yb3cY4H3dAa4LuB-"},{"date":"2013-04-26","title":"\u7720\u6c34 \u7f4c\u7c60\u846c\u8072\u7e6a\u96c6","price":"231","imageUrl":"http:\/\/www.kadokawa.com.tw\/Upload\/12488710045474981.jpg","link":"http:\/\/www.kadokawa.com.tw\/p1-products_detail.php?id=ca7feZr9BCaHj2Md9dVDuIgG9Nzr6d_YBtwgWxwcE1wa"},{"date":"2013-04-27","title":"\u9999\u6e2f\u6f6e\u6d41\u73a9\u7f8e\u5718","price":"185","imageUrl":"http:\/\/www.kadokawa.com.tw\/Upload\/6818711318891567.jpg","link":"http:\/\/www.kadokawa.com.tw\/p1-products_detail.php?id=731aKe4wOvCsQBShreBSmBizqkNsXaW0a6j8eVQj4OEL"},{"date":"2013-04-28","title":"\u611b\u4e0a\u9b06\u9905\u7c89\uff1a\u8d85EASY\u768492\u7a2e\u9ede\u5fc3","price":"165","imageUrl":"http:\/\/www.kadokawa.com.tw\/Upload\/1148998269799655.jpg","link":"http:\/\/www.kadokawa.com.tw\/p1-products_detail.php?id=a183zT7T-ganMS_7vaqb_xqIXvqMsnv83xriPUBRSplt"},{"date":"2013-04-29","title":"\u60e1\u9b54\u9ad8\u6821D\u00d7D (1)","price":"119","imageUrl":"http:\/\/www.kadokawa.com.tw\/Upload\/448147297673543.jpg","link":"http:\/\/www.kadokawa.com.tw\/p1-products_detail.php?id=ef5axsOOOu_K92kepCQ9rePIikJPGQ8rv76-mvcvA6aq"}]}