{"name":"kadokawa","bookList":[{"date":"2013-04-15","title":"\u65e5\u5e38 (1)","price":"73","imageUrl":"http:\/\/www.kadokawa.com.tw\/Upload\/109464112654127450.jpg","link":"http:\/\/www.kadokawa.com.tw\/p1-products_detail.php?id=9969fO_wILjCLn1pbhXkh3gK2DFn1cNpXwsgDnze0gE"},{"date":"2013-04-16","title":"\u5e78\u798f\u4e09\u9846\u661f \u5275\u4f5c\u5c0f\u8aaa","price":"165","imageUrl":"http:\/\/www.kadokawa.com.tw\/Upload\/product_201206111434171.jpg","link":"http:\/\/www.kadokawa.com.tw\/p1-products_detail.php?id=b1ecwpbw4rVTPpb4EktlQkmqDqGf3WBYYffjKSGV3DLX"},{"date":"2013-04-17","title":"\u8d85\u8089\u756b\u96c6 \u65b0\u6708  \u2014SHINGETSU\u2014","price":"277","imageUrl":"http:\/\/www.kadokawa.com.tw\/Upload\/119471119769112475.jpg","link":"http:\/\/www.kadokawa.com.tw\/p1-products_detail.php?id=62d62wwD8SVSXZYJ6bZJroupmxjzxIrnYnpu2NHCWC5B"},{"date":"2013-04-18","title":"\u5287\u5718\uff01Theatre","price":"172","imageUrl":"http:\/\/www.kadokawa.com.tw\/Upload\/product_201206151814551.jpg","link":"http:\/\/www.kadokawa.com.tw\/p1-products_detail.php?id=5a80oGA1Vm4CZwxm0NRxhYvGKU_0LkThvEXUKXBdet5P"},{"date":"2013-04-19","title":"FLY\uff0cDADDY\uff0cFLY","price":"145","imageUrl":"http:\/\/www.kadokawa.com.tw\/Upload\/8697577296116993.jpg","link":"http:\/\/www.kadokawa.com.tw\/p1-products_detail.php?id=066fFyYtkUsdMbh_zVD0Js7567rN8MCaDuo7cCGCHh_M"},{"date":"2013-04-20","title":"\u7f85\u99ac\u6d74\u5834 (\uff29)","price":"79","imageUrl":"http:\/\/www.kadokawa.com.tw\/Upload\/598577590866982.jpg","link":"http:\/\/www.kadokawa.com.tw\/p1-products_detail.php?id=1704sKmwpFjLcnhOPf1PswWjdVSqVHm1M7d-P9u0I2np"},{"date":"2013-04-21","title":"\u4e16\u754c\u4e00\u521d\u6200 \uff5e\u5c0f\u91ce\u5bfa\u5f8b\u7684\u60c5\u6cc1\uff5e","price":"79","imageUrl":"http:\/\/www.kadokawa.com.tw\/Upload\/711818996754257.jpg","link":"http:\/\/www.kadokawa.com.tw\/p1-products_detail.php?id=d3c25yKANkqw13n8Xv1v-l_sMt_sVTt1RD0Bu338rAQX"},{"date":"2013-04-22","title":"\u9b54\u528d\u59ec\uff01 (1)","price":"73","imageUrl":"http:\/\/www.kadokawa.com.tw\/Upload\/516535982881403.jpg","link":"http:\/\/www.kadokawa.com.tw\/p1-products_detail.php?id=6722-6Pz-NXJZ1SgpsrmOQCghotRtPw8FGrjEGdFmJ4"},{"date":"2013-04-23","title":"\u6d41\u6dda\u7684\u7d42\u7a76\u662f\u59b3","price":"158","imageUrl":"http:\/\/www.kadokawa.com.tw\/Upload\/product_201205231532411.jpg","link":"http:\/\/www.kadokawa.com.tw\/p1-products_detail.php?id=9f3dTCzLu6FI3B2qx0o6ryc2PCDzOr8TPs1oukXEEZg2"}]}