{"name":"sanmin","bookList":[{"date":"2015-02-16","title":"\u8f15\u9b06\u5b78\u82f1\u8a9e\u8a5e\u5f59 Vocabulary i...","price":"191","imageUrl":"http:\/\/123.51.221.159:81\/Assets\/product_images\/962\/962070372.jpg","link":"http:\/\/www.m.sanmin.com.tw\/Product\/Index\/99v155F6i106V7G109J71w111n122lTYvTMd146ZqM"},{"date":"2015-02-17","title":"\u770b\u770b\u4eba\u5bb6\u6eab\u5dde\u4eba","price":"185","imageUrl":"http:\/\/123.51.221.159:81\/Assets\/product_images\/986\/986595189.jpg","link":"http:\/\/www.m.sanmin.com.tw\/Product\/Index\/99R155M6v106L87I108w73k107e130ATNwXRy113HwZ"},{"date":"2015-02-18","title":"\u89aa\u624b\u4f5c\u306e\u7c21\u55ae\u512a\u96c5\u6b3e\u767d\u7d17&amp;amp;\u665a\u79ae\u670d","price":"383","imageUrl":"http:\/\/122.146.57.161\/Assets\/product_images\/986\/986302173.jpg","link":"http:\/\/www.m.sanmin.com.tw\/Product\/Index\/99b155g6C104r79d103r73g110P121MUPxVRp89DqN"},{"date":"2015-02-19","title":"\u72d7\u72d7\u9019\u6a23\u6559\uff0c\u4e3b\u4eba\u597d\u8f15\u9b06","price":"185","imageUrl":"http:\/\/113.196.56.91\/Assets\/product_images\/986\/986185729.jpg","link":"http:\/\/www.m.sanmin.com.tw\/Product\/Index\/99T155Z7a100U63g109C72U109T124mUReDUq178TmJ"},{"date":"2015-02-20","title":"\u76e1\u529b\u5c31\u597d\uff1a\u5929\u584c\u4e0b\u4f86\u53c8\u600e\u6a23!","price":"145","imageUrl":"http:\/\/113.196.56.91\/Assets\/product_images\/986\/986271116.jpg","link":"http:\/\/www.m.sanmin.com.tw\/Product\/Index\/99i155t8K105J7R107F65Y109T129dMGeUXc164RnV"},{"date":"2015-02-21","title":"\u8857\u8c93","price":"383","imageUrl":"http:\/\/113.196.56.95\/Assets\/product_images\/962\/962043625.jpg","link":"http:\/\/www.m.sanmin.com.tw\/Product\/Index\/99Q155x6V106D7b109D71i111B121YZRrKJq246ZqY"},{"date":"2015-02-22","title":"\u65b0\u591a\u76ca\u6838\u5fc3\u55ae\u5b57\u53e3\u888b\u672c","price":"263","imageUrl":"http:\/\/113.196.56.91\/Assets\/product_images\/986\/986271444.jpg","link":"http:\/\/www.m.sanmin.com.tw\/Product\/Index\/99h155S6F102g88y105F73M106I127HPWcAMx228WvN"}]}