{"name":"sanmin","bookList":[{"date":"2014-03-29","title":"\u5716\u89e3\u6211\u7684\u7b2c\u4e00\u5802\u884c\u92b7\u8ab2\uff1a\u7b49\u4eba\u6559\uff0c\u4e0d\u5982\u81ea\u5df1\u5077...","price":"164","imageUrl":"http:\/\/123.51.221.156\/Assets\/product_images\/986\/986578502.jpg","link":"http:\/\/www.sanmin.com.tw\/page-product.asp?pf_id=004144108"},{"date":"2014-03-30","title":"\u6a61\u76ae\u5370\u7ae0\u96d5\u523b\u901f\u5b78\uff0e10\u5206\u9418\u4e0a\u624b\uff01","price":"264","imageUrl":"http:\/\/113.196.56.95\/Assets\/product_images\/962\/962145182.jpg","link":"http:\/\/www.sanmin.com.tw\/page-product.asp?pf_id=004024653"},{"date":"2014-03-31","title":"\u516b\u9762\u73b2\u74cf\u5de6\u53f3\u9022\u6e90\u5fa1\u5fc3\u8853","price":"217","imageUrl":"http:\/\/113.196.56.91\/Assets\/product_images\/957\/957800535.jpg","link":"http:\/\/www.sanmin.com.tw\/page-product.asp?pf_id=004119388"}]}