{"name":"sanmin","bookList":[{"date":"2015-11-02","title":"\u80b2\u7f8e\u5abd\u5abd\u7684\u8d85\u4eba\u6c23\u52d5\u7269\u751c\u751c\u5708","price":"185","imageUrl":"http:\/\/123.51.221.158:81\/Assets\/product_images\/986\/986578332.jpg","link":"http:\/\/www.m.sanmin.com.tw\/Product\/Index\/99w155P5p101N88H103U68l112w127eEAmCPi87DkN"},{"date":"2015-11-03","title":"\u66fc\u54c8\u9813\u79c1\u5730\u5716\uff1a75\u4f4d\u7d10\u7d04\u5ba2\uff0c\u4ee5\u5730\u5716\u8a34\u8aaa\u4ed6...","price":"224","imageUrl":"http:\/\/122.146.57.161\/Assets\/product_images\/986\/986361153.jpg","link":"http:\/\/www.m.sanmin.com.tw\/Product\/Index\/99g155F5g101g72O106m67B105q124RNWsOFc163KsL"},{"date":"2015-11-04","title":"\u501f\u529b\u6dd8\u91d1!\u6700\u5438\u5229\u7684\u9214\u7d1a\u9b5a\u6c60\u8cfa\u9322\u8853","price":"211","imageUrl":"http:\/\/123.51.221.158:81\/Assets\/product_images\/986\/986271286.jpg","link":"http:\/\/www.m.sanmin.com.tw\/Product\/Index\/99g155C7B105g87e103I69P111r129OCDuMPe145CfC"}]}