{"name":"sanmin","bookList":[{"date":"2014-10-30","title":"\u671d\u9bae\u805e\u898b\u9304","price":"409","imageUrl":"http:\/\/113.196.56.95\/Assets\/product_images\/962\/962043313.jpg","link":"http:\/\/www.m.sanmin.com.tw\/Product\/Index\/99v155B6i100N63l104b70O106p130UKUsSTe1551BgY"},{"date":"2014-10-30","title":"\u6cd5\u8001\u6642\u4ee3\u7684\u57c3\u53ca\uff0d\u4eba\u985e\u6587\u660e\u5c0f\u767e\u79d12","price":"165","imageUrl":"http:\/\/122.146.57.160\/Assets\/product_images\/957\/957142609.jpg","link":"http:\/\/www.m.sanmin.com.tw\/Product\/Index\/99Y155L10U102J52i100D65C106S127eZMaLHt1786VeC"},{"date":"2014-10-31","title":"\u6162\u6c7a\u96e2\u653e\uff01\u7d66\u5b69\u5b50\u6700\u6709\u611f\u7684\u9ad8EQ\u6559\u990a","price":"172","imageUrl":"http:\/\/122.146.57.160\/Assets\/product_images\/986\/986271446.jpg","link":"http:\/\/www.m.sanmin.com.tw\/Product\/Index\/99D155e6w102s79g101V71u105l123uOFfJOi1060LoB"},{"date":"2014-11-01","title":"\u4eac\u90fd\u7684\u6587\u5177\u6642\u5149","price":"218","imageUrl":"http:\/\/122.146.57.160\/Assets\/product_images\/986\/986361018.jpg","link":"http:\/\/www.m.sanmin.com.tw\/Product\/Index\/99f155y6v105U52g102s68I107C121hKOiHVi756KvK"},{"date":"2014-11-02","title":"\u5716\u89e3\u8056\u7d93","price":"251","imageUrl":"http:\/\/122.146.57.160\/Assets\/product_images\/986\/986594268.jpg","link":"http:\/\/www.m.sanmin.com.tw\/Product\/Index\/99r155Y6N104P24l102h68X105J126HZTpPGn1591WcO"},{"date":"2014-11-03","title":"1\u984c\u80cc4\u55ae\u5b57\uff01\u7528\u9078\u64c7\u984c\u7834\u89e37000\u55ae\u5b57","price":"263","imageUrl":"http:\/\/122.146.57.160\/Assets\/product_images\/986\/986271295.jpg","link":"http:\/\/www.m.sanmin.com.tw\/Product\/Index\/99B155S7K105z63n103C71h105D128OOUbKBi1210NpI"},{"date":"2014-11-04","title":"\u516c\u958b\u6c11\u9593\u547d\u7406\u85cf\u7d93","price":"231","imageUrl":"http:\/\/122.146.57.160\/Assets\/product_images\/986\/986608089.jpg","link":"http:\/\/www.m.sanmin.com.tw\/Product\/Index\/99u155l6e105G7y109r74a112m129PXYqARz23YbH"}]}