{"name":"sanmin","bookList":[{"date":"2014-01-04","title":"\u6211\u5728\u9996\u723e\u6162\u6162\u6563\u6b65\uff1a\u5c0f\u5df7\u53e4\u8e5f\u79c1\u65c5\u884c\uff0c\u5728\u5730\u4eba...","price":"218","imageUrl":"http:\/\/113.196.56.95\/Assets\/product_images\/986\/986185896.jpg","link":"http:\/\/www.sanmin.com.tw\/page-product.asp?pf_id=004032930"},{"date":"2014-01-05","title":"50\u6b72\u5f8c\uff0c\u9000\u800c\u4e0d\u4f11\u7684\u990a\u751f\u529b","price":"185","imageUrl":"http:\/\/113.196.56.95\/Assets\/product_images\/986\/986271333.jpg","link":"http:\/\/www.sanmin.com.tw\/page-product.asp?pf_id=003751859"},{"date":"2014-01-06","title":"\u7562\u696d5\u5e74\u6c7a\u5b9a\u4f60\u4e00\u751f\u7684\u6210\u6557","price":"172","imageUrl":"http:\/\/113.196.56.91\/Assets\/product_images\/957\/957713528.jpg","link":"http:\/\/www.sanmin.com.tw\/page-product.asp?pf_id=003907153"},{"date":"2014-01-07","title":"\u65b0\u591a\u76ca\u6e2c\u9a57\u77ed\u671f\u7279\u8a13\u73ed\uff1a\u6c92\u6642\u9593\u3001\u8a0e\u53ad\u82f1\u6587\u7684...","price":"158","imageUrl":"http:\/\/123.51.221.156\/Assets\/product_images\/986\/986185830.jpg","link":"http:\/\/www.sanmin.com.tw\/page-product.asp?pf_id=003759020"},{"date":"2014-01-08","title":"\u5716\u89e3\u65e5\u6587\u7684\u539f\u7406\uff1a\u7528\u65e5\u672c\u4eba\u7684\u601d\u7dad\u5b78\u597d\u65e5\u6587","price":"197","imageUrl":"http:\/\/123.51.221.156\/Assets\/product_images\/986\/986592736.jpg","link":"http:\/\/www.sanmin.com.tw\/page-product.asp?pf_id=003965866"},{"date":"2014-01-09","title":"620\u5104\u7f8e\u5143\u7684\u79d8\u5bc6\uff1a\u5df4\u83f2\u7279\u96ea\u7403\u50b3\u5947\u5168\u7d00\u9304","price":"297","imageUrl":"http:\/\/123.51.221.156\/Assets\/product_images\/986\/986271275.jpg","link":"http:\/\/www.sanmin.com.tw\/page-product.asp?pf_id=003448619"},{"date":"2014-01-10","title":"\u6b77\u53f2\u7684\u5bec\u5bb9","price":"297","imageUrl":"http:\/\/www.sanmin.com.tw\/Assets\/product_images\/986\/986595155.jpg","link":"http:\/\/www.sanmin.com.tw\/page-product.asp?pf_id=003983477"}]}