{"name":"taaze","bookList":[{"date":"2013-07-24","title":"\u54c8\u4f5bMBA\u6700\u60f3\u5b78\u7684\u5275\u696d\u50b3\u5947\uff1a3\u5e74\u5275\u51fa30...","price":"198","imageUrl":"http:\/\/media.taaze.tw\/showLargeImage.html?sc=11100647556","link":"http:\/\/www.taaze.tw\/sing.html?pid=11100647556"},{"date":"2013-07-25","title":"\u88f8\u57ce\uff1a\u7d14\u6b63\u90fd\u5e02\u5730\u65b9\u7684\u751f\u8207\u6b7b","price":"264","imageUrl":"http:\/\/media.taaze.tw\/showLargeImage.html?sc=11100621915","link":"http:\/\/www.taaze.tw\/sing.html?pid=11100621915"},{"date":"2013-07-26","title":"\u6392\u6bd2\u8212\u98df\u76db\u5bb4","price":"211","imageUrl":"http:\/\/media.taaze.tw\/showLargeImage.html?sc=11100617085","link":"http:\/\/www.taaze.tw\/sing.html?pid=11100617085"},{"date":"2013-07-27","title":"\u4e00\u624b\u638c\u63e1NEW TOEIC\u65b0\u591a\u76ca\u55ae\u5b57\uff08\u9644...","price":"211","imageUrl":"http:\/\/media.taaze.tw\/showLargeImage.html?sc=11100650428","link":"http:\/\/www.taaze.tw\/sing.html?pid=11100650428"},{"date":"2013-07-28","title":"\u5225\u7576\u6b63\u5e38\u7684\u50bb\u74dc\uff08\u5168\u65b0\u7b2c\u4e8c\u7248\uff09","price":"198","imageUrl":"http:\/\/media.taaze.tw\/showLargeImage.html?sc=11100180233","link":"http:\/\/www.taaze.tw\/sing.html?pid=11100180233"}]}