{"name":"taaze","bookList":[{"date":"2015-08-24","title":"50\u500b\u8b93Apple Watch\u66f4\u597d\u73a9\u7684\u8a2d...","price":"40","imageUrl":"http:\/\/media.taaze.tw\/showLargeImage.html?sc=14100014837","link":"http:\/\/www.taaze.tw\/sing.html?pid=14100014837"},{"date":"2015-08-28","title":"\u7a81\u7834\u66f8\u8a8cBreakazine 5-6\u6708\u865f...","price":"80","imageUrl":"http:\/\/media.taaze.tw\/showLargeImage.html?sc=25100002877","link":"http:\/\/www.taaze.tw\/sing.html?pid=25100002877"},{"date":"2015-08-24","title":"\u7063\u751f\u56de\u5bb6","price":"238","imageUrl":"http:\/\/media.taaze.tw\/showLargeImage.html?sc=11100719233","link":"http:\/\/www.taaze.tw\/sing.html?pid=11100719233"},{"date":"2015-08-25","title":"\u7d93\u6fdf\u5b78\u95dc\u6211\u4ec0\u9ebc\u4e8b\uff01\u4f46\u6708\u981822K\u5f88\u6709\u4e8b\uff1a\u70ba...","price":"185","imageUrl":"http:\/\/media.taaze.tw\/showLargeImage.html?sc=11100738314","link":"http:\/\/www.taaze.tw\/sing.html?pid=11100738314"},{"date":"2015-08-26","title":"\u6c42\u771f\uff1a\u81fa\u5927\u6700\u53d7\u6b61\u8fce\u7684\u54f2\u5b78\u516c\u958b\u8ab2","price":"185","imageUrl":"http:\/\/media.taaze.tw\/showLargeImage.html?sc=11100734554","link":"http:\/\/www.taaze.tw\/sing.html?pid=11100734554"},{"date":"2015-08-27","title":"\u4eba\u751f\u5982\u679c\u662f\u4e00\u500b\uff08 \uff09\uff0c\u4f60\u60f3\u586b\u5165\u4ec0\u9ebc\uff1f","price":"185","imageUrl":"http:\/\/media.taaze.tw\/showLargeImage.html?sc=11100728912","link":"http:\/\/www.taaze.tw\/sing.html?pid=11100728912"},{"date":"2015-08-28","title":"\u9060\u5927\u524d\u7a0b\uff08\u53c8\u540d\u5b64\u661f\u8840\u6dda\uff0c\u72c4\u66f4\u65af\u50b3\u5947\u4ee3\u8868\u4f5c...","price":"383","imageUrl":"http:\/\/media.taaze.tw\/showLargeImage.html?sc=11100720185","link":"http:\/\/www.taaze.tw\/sing.html?pid=11100720185"},{"date":"2015-08-29","title":"\u65b0\u98df\u611f\uff01\u9eb5\u5305\u6a5f\u8b8a\u51fa85\u9053\u4e2d\u897f\u6599\u7406","price":"224","imageUrl":"http:\/\/media.taaze.tw\/showLargeImage.html?sc=11100712156","link":"http:\/\/www.taaze.tw\/sing.html?pid=11100712156"},{"date":"2015-08-30","title":"\u53b2\u5bb3\uff01\u5225\u5c0f\u770b\u7cfb\u7d71\u5bb6\u5177\uff1a \u8a2d\u8a08\u5e2b\u63a8\u85a6\u611b\u7528\uff0c...","price":"263","imageUrl":"http:\/\/media.taaze.tw\/showLargeImage.html?sc=11100729727","link":"http:\/\/www.taaze.tw\/sing.html?pid=11100729727"}]}