{"name":"taaze","bookList":[{"date":"2016-01-09","title":"\u8d85\u9ad8\u9f61\u793e\u6703\u7684\u6d88\u8cbb\u884c\u70ba\u5b78\uff1a\u638c\u63e1\u4e2d\u9ad8\u9f61\u65cf\u7fa4\u5fc3...","price":"238","imageUrl":"http:\/\/media.taaze.tw\/showLargeImage.html?sc=11100754052","link":"http:\/\/www.taaze.tw\/sing.html?pid=11100754052"},{"date":"2016-01-10","title":"\u95dc\u65bc\u8003\u8a66\uff0c\u4f60\u7528\u7684\u65b9\u6cd5\u90fd\u662f\u932f\u7684\uff1a\u65e5\u672c\u8003\u8a66\u4e4b...","price":"165","imageUrl":"http:\/\/media.taaze.tw\/showLargeImage.html?sc=11100433060","link":"http:\/\/www.taaze.tw\/sing.html?pid=11100433060"}]}